{
  "id": "f01bebe3-c5ec-426d-bd14-9f1a1fa1c4ed",
  "prevId": "9bed2bc9-2f81-461b-9934-da27afae3fdd",
  "version": "7",
  "dialect": "postgresql",
  "tables": {
    "public.embeddings": {
      "name": "embeddings",
      "schema": "",
      "columns": {
        "id": {
          "name": "id",
          "type": "uuid",
          "primaryKey": true,
          "notNull": true,
          "default": "gen_random_uuid()"
        },
        "source_type": {
          "name": "source_type",
          "type": "text",
          "primaryKey": false,
          "notNull": true
        },
        "source_id": {
          "name": "source_id",
          "type": "text",
          "primaryKey": false,
          "notNull": true
        },
        "embedding_model": {
          "name": "embedding_model",
          "type": "text",
          "primaryKey": false,
          "notNull": true
        },
        "content": {
          "name": "content",
          "type": "text",
          "primaryKey": false,
          "notNull": true
        },
        "embedding": {
          "name": "embedding",
          "type": "vector(1536)",
          "primaryKey": false,
          "notNull": true
        },
        "created_at": {
          "name": "created_at",
          "type": "timestamp with time zone",
          "primaryKey": false,
          "notNull": true,
          "default": "now()"
        }
      },
      "indexes": {
        "embeddings_source_lookup_idx": {
          "name": "embeddings_source_lookup_idx",
          "columns": [
            {
              "expression": "source_type",
              "isExpression": false,
              "asc": true,
              "nulls": "last"
            },
            {
              "expression": "source_id",
              "isExpression": false,
              "asc": true,
              "nulls": "last"
            },
            {
              "expression": "embedding_model",
              "isExpression": false,
              "asc": true,
              "nulls": "last"
            }
          ],
          "isUnique": true,
          "concurrently": false,
          "method": "btree",
          "with": {}
        },
        "embeddings_embedding_cosine_idx": {
          "name": "embeddings_embedding_cosine_idx",
          "columns": [
            {
              "expression": "embedding",
              "isExpression": false,
              "asc": true,
              "nulls": "last",
              "opclass": "vector_cosine_ops"
            }
          ],
          "isUnique": false,
          "concurrently": false,
          "method": "hnsw",
          "with": {}
        }
      },
      "foreignKeys": {},
      "compositePrimaryKeys": {},
      "uniqueConstraints": {},
      "policies": {},
      "checkConstraints": {},
      "isRLSEnabled": false
    },
    "public.users": {
      "name": "users",
      "schema": "",
      "columns": {
        "id": {
          "name": "id",
          "type": "uuid",
          "primaryKey": true,
          "notNull": true,
          "default": "gen_random_uuid()"
        },
        "email": {
          "name": "email",
          "type": "text",
          "primaryKey": false,
          "notNull": true
        },
        "display_name": {
          "name": "display_name",
          "type": "text",
          "primaryKey": false,
          "notNull": false
        },
        "created_at": {
          "name": "created_at",
          "type": "timestamp with time zone",
          "primaryKey": false,
          "notNull": true,
          "default": "now()"
        },
        "updated_at": {
          "name": "updated_at",
          "type": "timestamp with time zone",
          "primaryKey": false,
          "notNull": true,
          "default": "now()"
        }
      },
      "indexes": {},
      "foreignKeys": {},
      "compositePrimaryKeys": {},
      "uniqueConstraints": {
        "users_email_unique": {
          "name": "users_email_unique",
          "nullsNotDistinct": false,
          "columns": ["email"]
        }
      },
      "policies": {},
      "checkConstraints": {},
      "isRLSEnabled": false
    }
  },
  "enums": {},
  "schemas": {},
  "sequences": {},
  "roles": {},
  "policies": {},
  "views": {},
  "_meta": {
    "columns": {},
    "schemas": {},
    "tables": {}
  }
}
